[
  {
    "name": "12. Nicolás Covarrubias Portero",
    "position_raw": "Portero",
    "position": "ARQ",
    "age": "N/A",
    "number": "N/A",
    "market_value": "N/A",
    "source": "https://enelcamarin.cl/joomsport_team/a-oriente/?sid=166009"
  },
  {
    "name": "1. Lucas Guimpert Portero",
    "position_raw": "Portero",
    "position": "ARQ",
    "age": "N/A",
    "number": "N/A",
    "market_value": "N/A",
    "source": "https://enelcamarin.cl/joomsport_team/a-oriente/?sid=166009"
  },
  {
    "name": "Michael Ahumada Portero",
    "position_raw": "Portero",
    "position": "ARQ",
    "age": "N/A",
    "number": "N/A",
    "market_value": "N/A",
    "source": "https://enelcamarin.cl/joomsport_team/a-oriente/?sid=166009"
  },
  {
    "name": "1. Javier Cubillos Portero",
    "position_raw": "Portero",
    "position": "ARQ",
    "age": "N/A",
    "number": "N/A",
    "market_value": "N/A",
    "source": "https://enelcamarin.cl/joomsport_team/a-oriente/?sid=166009"
  },
  {
    "name": "José Tomás Martínez Portero",
    "position_raw": "Portero",
    "position": "ARQ",
    "age": "N/A",
    "number": "N/A",
    "market_value": "N/A",
    "source": "https://enelcamarin.cl/joomsport_team/a-oriente/?sid=166009"
  },
  {
    "name": "Rodrigo Cancino Portero",
    "position_raw": "Portero",
    "position": "ARQ",
    "age": "N/A",
    "number": "N/A",
    "market_value": "N/A",
    "source": "https://enelcamarin.cl/joomsport_team/a-oriente/?sid=166009"
  },
  {
    "name": "Bryan Escobar (2002) Portero",
    "position_raw": "Portero",
    "position": "ARQ",
    "age": "N/A",
    "number": "N/A",
    "market_value": "N/A",
    "source": "https://enelcamarin.cl/joomsport_team/a-oriente/?sid=166009"
  },
  {
    "name": "Luis Guzmán Morales Portero",
    "position_raw": "Portero",
    "position": "ARQ",
    "age": "N/A",
    "number": "N/A",
    "market_value": "N/A",
    "source": "https://enelcamarin.cl/joomsport_team/a-oriente/?sid=166009"
  },
  {
    "name": "Benjamín Guerrero Portero",
    "position_raw": "Portero",
    "position": "ARQ",
    "age": "N/A",
    "number": "N/A",
    "market_value": "N/A",
    "source": "https://enelcamarin.cl/joomsport_team/a-oriente/?sid=166009"
  },
  {
    "name": "Alonso Montecinos Portero",
    "position_raw": "Portero",
    "position": "ARQ",
    "age": "N/A",
    "number": "N/A",
    "market_value": "N/A",
    "source": "https://enelcamarin.cl/joomsport_team/a-oriente/?sid=166009"
  },
  {
    "name": "Felipe Asenjo Defensa",
    "position_raw": "Defensa",
    "position": "DEF",
    "age": "N/A",
    "number": "N/A",
    "market_value": "N/A",
    "source": "https://enelcamarin.cl/joomsport_team/a-oriente/?sid=166009"
  },
  {
    "name": "Gustavo Javier Gómez Defensa",
    "position_raw": "Defensa",
    "position": "DEF",
    "age": "N/A",
    "number": "N/A",
    "market_value": "N/A",
    "source": "https://enelcamarin.cl/joomsport_team/a-oriente/?sid=166009"
  },
  {
    "name": "Abraham Lobos Defensa",
    "position_raw": "Defensa",
    "position": "DEF",
    "age": "N/A",
    "number": "N/A",
    "market_value": "N/A",
    "source": "https://enelcamarin.cl/joomsport_team/a-oriente/?sid=166009"
  },
  {
    "name": "Marcelo Cubillos Defensa",
    "position_raw": "Defensa",
    "position": "DEF",
    "age": "N/A",
    "number": "N/A",
    "market_value": "N/A",
    "source": "https://enelcamarin.cl/joomsport_team/a-oriente/?sid=166009"
  },
  {
    "name": "Franco Polanco Defensa",
    "position_raw": "Defensa",
    "position": "DEF",
    "age": "N/A",
    "number": "N/A",
    "market_value": "N/A",
    "source": "https://enelcamarin.cl/joomsport_team/a-oriente/?sid=166009"
  },
  {
    "name": "Vicente Barría Defensa",
    "position_raw": "Defensa",
    "position": "DEF",
    "age": "N/A",
    "number": "N/A",
    "market_value": "N/A",
    "source": "https://enelcamarin.cl/joomsport_team/a-oriente/?sid=166009"
  },
  {
    "name": "Daglas Maldonado Defensa",
    "position_raw": "Defensa",
    "position": "DEF",
    "age": "N/A",
    "number": "N/A",
    "market_value": "N/A",
    "source": "https://enelcamarin.cl/joomsport_team/a-oriente/?sid=166009"
  },
  {
    "name": "18. Antonio Bernedo Defensa",
    "position_raw": "Defensa",
    "position": "DEF",
    "age": "N/A",
    "number": "N/A",
    "market_value": "N/A",
    "source": "https://enelcamarin.cl/joomsport_team/a-oriente/?sid=166009"
  },
  {
    "name": "Benjamín Troncoso Defensa",
    "position_raw": "Defensa",
    "position": "DEF",
    "age": "N/A",
    "number": "N/A",
    "market_value": "N/A",
    "source": "https://enelcamarin.cl/joomsport_team/a-oriente/?sid=166009"
  },
  {
    "name": "7. Diego Araya Defensa",
    "position_raw": "Defensa",
    "position": "DEF",
    "age": "N/A",
    "number": "N/A",
    "market_value": "N/A",
    "source": "https://enelcamarin.cl/joomsport_team/a-oriente/?sid=166009"
  },
  {
    "name": "Ignacio Saldías Defensa",
    "position_raw": "Defensa",
    "position": "DEF",
    "age": "N/A",
    "number": "N/A",
    "market_value": "N/A",
    "source": "https://enelcamarin.cl/joomsport_team/a-oriente/?sid=166009"
  },
  {
    "name": "Francisco Villarroel Defensa",
    "position_raw": "Defensa",
    "position": "DEF",
    "age": "N/A",
    "number": "N/A",
    "market_value": "N/A",
    "source": "https://enelcamarin.cl/joomsport_team/a-oriente/?sid=166009"
  },
  {
    "name": "Danilo Bustamante Defensa",
    "position_raw": "Defensa",
    "position": "DEF",
    "age": "N/A",
    "number": "N/A",
    "market_value": "N/A",
    "source": "https://enelcamarin.cl/joomsport_team/a-oriente/?sid=166009"
  },
  {
    "name": "2. Julián Gálvez Defensa",
    "position_raw": "Defensa",
    "position": "DEF",
    "age": "N/A",
    "number": "N/A",
    "market_value": "N/A",
    "source": "https://enelcamarin.cl/joomsport_team/a-oriente/?sid=166009"
  },
  {
    "name": "Sebastián Leiva Defensa",
    "position_raw": "Defensa",
    "position": "DEF",
    "age": "N/A",
    "number": "N/A",
    "market_value": "N/A",
    "source": "https://enelcamarin.cl/joomsport_team/a-oriente/?sid=166009"
  },
  {
    "name": "Kevin Aranda Defensa",
    "position_raw": "Defensa",
    "position": "DEF",
    "age": "N/A",
    "number": "N/A",
    "market_value": "N/A",
    "source": "https://enelcamarin.cl/joomsport_team/a-oriente/?sid=166009"
  },
  {
    "name": "Rodrigo Vidal Defensa",
    "position_raw": "Defensa",
    "position": "DEF",
    "age": "N/A",
    "number": "N/A",
    "market_value": "N/A",
    "source": "https://enelcamarin.cl/joomsport_team/a-oriente/?sid=166009"
  },
  {
    "name": "José Luis Aedo Defensa",
    "position_raw": "Defensa",
    "position": "DEF",
    "age": "N/A",
    "number": "N/A",
    "market_value": "N/A",
    "source": "https://enelcamarin.cl/joomsport_team/a-oriente/?sid=166009"
  },
  {
    "name": "Dery Varela Defensa",
    "position_raw": "Defensa",
    "position": "DEF",
    "age": "N/A",
    "number": "N/A",
    "market_value": "N/A",
    "source": "https://enelcamarin.cl/joomsport_team/a-oriente/?sid=166009"
  },
  {
    "name": "Maximiliano Godoy Forne Defensa",
    "position_raw": "Defensa",
    "position": "DEF",
    "age": "N/A",
    "number": "N/A",
    "market_value": "N/A",
    "source": "https://enelcamarin.cl/joomsport_team/a-oriente/?sid=166009"
  },
  {
    "name": "Jordan Olea Defensa",
    "position_raw": "Defensa",
    "position": "DEF",
    "age": "N/A",
    "number": "N/A",
    "market_value": "N/A",
    "source": "https://enelcamarin.cl/joomsport_team/a-oriente/?sid=166009"
  },
  {
    "name": "Nicolás Guerra Villalobos Volante",
    "position_raw": "Volante",
    "position": "MED",
    "age": "N/A",
    "number": "N/A",
    "market_value": "N/A",
    "source": "https://enelcamarin.cl/joomsport_team/a-oriente/?sid=166009"
  },
  {
    "name": "Víctor Bravo Volante",
    "position_raw": "Volante",
    "position": "MED",
    "age": "N/A",
    "number": "N/A",
    "market_value": "N/A",
    "source": "https://enelcamarin.cl/joomsport_team/a-oriente/?sid=166009"
  },
  {
    "name": "Joshua Villarroel Volante",
    "position_raw": "Volante",
    "position": "MED",
    "age": "N/A",
    "number": "N/A",
    "market_value": "N/A",
    "source": "https://enelcamarin.cl/joomsport_team/a-oriente/?sid=166009"
  },
  {
    "name": "Martín Pérez Volante",
    "position_raw": "Volante",
    "position": "MED",
    "age": "N/A",
    "number": "N/A",
    "market_value": "N/A",
    "source": "https://enelcamarin.cl/joomsport_team/a-oriente/?sid=166009"
  },
  {
    "name": "Carlos Garay Volante",
    "position_raw": "Volante",
    "position": "MED",
    "age": "N/A",
    "number": "N/A",
    "market_value": "N/A",
    "source": "https://enelcamarin.cl/joomsport_team/a-oriente/?sid=166009"
  },
  {
    "name": "Esteban Guzmán Volante",
    "position_raw": "Volante",
    "position": "MED",
    "age": "N/A",
    "number": "N/A",
    "market_value": "N/A",
    "source": "https://enelcamarin.cl/joomsport_team/a-oriente/?sid=166009"
  },
  {
    "name": "Benjamín Maureira Volante",
    "position_raw": "Volante",
    "position": "MED",
    "age": "N/A",
    "number": "N/A",
    "market_value": "N/A",
    "source": "https://enelcamarin.cl/joomsport_team/a-oriente/?sid=166009"
  },
  {
    "name": "10. Jordan Moreno Volante",
    "position_raw": "Volante",
    "position": "MED",
    "age": "N/A",
    "number": "N/A",
    "market_value": "N/A",
    "source": "https://enelcamarin.cl/joomsport_team/a-oriente/?sid=166009"
  },
  {
    "name": "Sebastián Muñoz Tejas Volante",
    "position_raw": "Volante",
    "position": "MED",
    "age": "N/A",
    "number": "N/A",
    "market_value": "N/A",
    "source": "https://enelcamarin.cl/joomsport_team/a-oriente/?sid=166009"
  },
  {
    "name": "9. Ricardo Guerrero Castillo Volante",
    "position_raw": "Volante",
    "position": "MED",
    "age": "N/A",
    "number": "N/A",
    "market_value": "N/A",
    "source": "https://enelcamarin.cl/joomsport_team/a-oriente/?sid=166009"
  },
  {
    "name": "Esaú Burgos Volante",
    "position_raw": "Volante",
    "position": "MED",
    "age": "N/A",
    "number": "N/A",
    "market_value": "N/A",
    "source": "https://enelcamarin.cl/joomsport_team/a-oriente/?sid=166009"
  },
  {
    "name": "6. Martín Campos Volante",
    "position_raw": "Volante",
    "position": "MED",
    "age": "N/A",
    "number": "N/A",
    "market_value": "N/A",
    "source": "https://enelcamarin.cl/joomsport_team/a-oriente/?sid=166009"
  },
  {
    "name": "8. Ignacio Guerrero Volante",
    "position_raw": "Volante",
    "position": "MED",
    "age": "N/A",
    "number": "N/A",
    "market_value": "N/A",
    "source": "https://enelcamarin.cl/joomsport_team/a-oriente/?sid=166009"
  },
  {
    "name": "11. Víctor Caroca Volante",
    "position_raw": "Volante",
    "position": "MED",
    "age": "N/A",
    "number": "N/A",
    "market_value": "N/A",
    "source": "https://enelcamarin.cl/joomsport_team/a-oriente/?sid=166009"
  },
  {
    "name": "Marcello Calderón Volante",
    "position_raw": "Volante",
    "position": "MED",
    "age": "N/A",
    "number": "N/A",
    "market_value": "N/A",
    "source": "https://enelcamarin.cl/joomsport_team/a-oriente/?sid=166009"
  },
  {
    "name": "Brayan Quezada Volante",
    "position_raw": "Volante",
    "position": "MED",
    "age": "N/A",
    "number": "N/A",
    "market_value": "N/A",
    "source": "https://enelcamarin.cl/joomsport_team/a-oriente/?sid=166009"
  },
  {
    "name": "Diego Araya Volante",
    "position_raw": "Volante",
    "position": "MED",
    "age": "N/A",
    "number": "N/A",
    "market_value": "N/A",
    "source": "https://enelcamarin.cl/joomsport_team/a-oriente/?sid=166009"
  },
  {
    "name": "17. Sebastián Sasso Volante",
    "position_raw": "Volante",
    "position": "MED",
    "age": "N/A",
    "number": "N/A",
    "market_value": "N/A",
    "source": "https://enelcamarin.cl/joomsport_team/a-oriente/?sid=166009"
  },
  {
    "name": "Jesrrel Gálvez Volante",
    "position_raw": "Volante",
    "position": "MED",
    "age": "N/A",
    "number": "N/A",
    "market_value": "N/A",
    "source": "https://enelcamarin.cl/joomsport_team/a-oriente/?sid=166009"
  },
  {
    "name": "Ariel Pizarro Volante",
    "position_raw": "Volante",
    "position": "MED",
    "age": "N/A",
    "number": "N/A",
    "market_value": "N/A",
    "source": "https://enelcamarin.cl/joomsport_team/a-oriente/?sid=166009"
  },
  {
    "name": "10. Alans Yañez Volante",
    "position_raw": "Volante",
    "position": "MED",
    "age": "N/A",
    "number": "N/A",
    "market_value": "N/A",
    "source": "https://enelcamarin.cl/joomsport_team/a-oriente/?sid=166009"
  },
  {
    "name": "Lucas Rojas Volante",
    "position_raw": "Volante",
    "position": "MED",
    "age": "N/A",
    "number": "N/A",
    "market_value": "N/A",
    "source": "https://enelcamarin.cl/joomsport_team/a-oriente/?sid=166009"
  },
  {
    "name": "Mauricio Aravena Volante",
    "position_raw": "Volante",
    "position": "MED",
    "age": "N/A",
    "number": "N/A",
    "market_value": "N/A",
    "source": "https://enelcamarin.cl/joomsport_team/a-oriente/?sid=166009"
  },
  {
    "name": "Agustín Flores Volante",
    "position_raw": "Volante",
    "position": "MED",
    "age": "N/A",
    "number": "N/A",
    "market_value": "N/A",
    "source": "https://enelcamarin.cl/joomsport_team/a-oriente/?sid=166009"
  },
  {
    "name": "Brian Sevich Volante",
    "position_raw": "Volante",
    "position": "MED",
    "age": "N/A",
    "number": "N/A",
    "market_value": "N/A",
    "source": "https://enelcamarin.cl/joomsport_team/a-oriente/?sid=166009"
  },
  {
    "name": "Emir González Volante",
    "position_raw": "Volante",
    "position": "MED",
    "age": "N/A",
    "number": "N/A",
    "market_value": "N/A",
    "source": "https://enelcamarin.cl/joomsport_team/a-oriente/?sid=166009"
  },
  {
    "name": "Darío Aravena Volante",
    "position_raw": "Volante",
    "position": "MED",
    "age": "N/A",
    "number": "N/A",
    "market_value": "N/A",
    "source": "https://enelcamarin.cl/joomsport_team/a-oriente/?sid=166009"
  },
  {
    "name": "Víctor Cisterna Volante",
    "position_raw": "Volante",
    "position": "MED",
    "age": "N/A",
    "number": "N/A",
    "market_value": "N/A",
    "source": "https://enelcamarin.cl/joomsport_team/a-oriente/?sid=166009"
  },
  {
    "name": "Jorge Cid Volante",
    "position_raw": "Volante",
    "position": "MED",
    "age": "N/A",
    "number": "N/A",
    "market_value": "N/A",
    "source": "https://enelcamarin.cl/joomsport_team/a-oriente/?sid=166009"
  },
  {
    "name": "Dhariel Núñez Volante",
    "position_raw": "Volante",
    "position": "MED",
    "age": "N/A",
    "number": "N/A",
    "market_value": "N/A",
    "source": "https://enelcamarin.cl/joomsport_team/a-oriente/?sid=166009"
  },
  {
    "name": "Francisco Valenzuela Volante",
    "position_raw": "Volante",
    "position": "MED",
    "age": "N/A",
    "number": "N/A",
    "market_value": "N/A",
    "source": "https://enelcamarin.cl/joomsport_team/a-oriente/?sid=166009"
  },
  {
    "name": "21. Gabriel Gómez Delantero",
    "position_raw": "Delantero",
    "position": "DEL",
    "age": "N/A",
    "number": "N/A",
    "market_value": "N/A",
    "source": "https://enelcamarin.cl/joomsport_team/a-oriente/?sid=166009"
  },
  {
    "name": "Ronald Melo Delantero",
    "position_raw": "Delantero",
    "position": "DEL",
    "age": "N/A",
    "number": "N/A",
    "market_value": "N/A",
    "source": "https://enelcamarin.cl/joomsport_team/a-oriente/?sid=166009"
  },
  {
    "name": "Christopher Delgado Delantero",
    "position_raw": "Delantero",
    "position": "DEL",
    "age": "N/A",
    "number": "N/A",
    "market_value": "N/A",
    "source": "https://enelcamarin.cl/joomsport_team/a-oriente/?sid=166009"
  },
  {
    "name": "Sebastian Lara Delantero",
    "position_raw": "Delantero",
    "position": "DEL",
    "age": "N/A",
    "number": "N/A",
    "market_value": "N/A",
    "source": "https://enelcamarin.cl/joomsport_team/a-oriente/?sid=166009"
  },
  {
    "name": "Ignacio Muñoz Pérez Delantero",
    "position_raw": "Delantero",
    "position": "DEL",
    "age": "N/A",
    "number": "N/A",
    "market_value": "N/A",
    "source": "https://enelcamarin.cl/joomsport_team/a-oriente/?sid=166009"
  },
  {
    "name": "Tomás Navarro Delantero",
    "position_raw": "Delantero",
    "position": "DEL",
    "age": "N/A",
    "number": "N/A",
    "market_value": "N/A",
    "source": "https://enelcamarin.cl/joomsport_team/a-oriente/?sid=166009"
  },
  {
    "name": "José Recabal Delantero",
    "position_raw": "Delantero",
    "position": "DEL",
    "age": "N/A",
    "number": "N/A",
    "market_value": "N/A",
    "source": "https://enelcamarin.cl/joomsport_team/a-oriente/?sid=166009"
  },
  {
    "name": "18. John Araya Delantero",
    "position_raw": "Delantero",
    "position": "DEL",
    "age": "N/A",
    "number": "N/A",
    "market_value": "N/A",
    "source": "https://enelcamarin.cl/joomsport_team/a-oriente/?sid=166009"
  },
  {
    "name": "John Gómez Ruiz Delantero",
    "position_raw": "Delantero",
    "position": "DEL",
    "age": "N/A",
    "number": "N/A",
    "market_value": "N/A",
    "source": "https://enelcamarin.cl/joomsport_team/a-oriente/?sid=166009"
  },
  {
    "name": "Luciano Anzalone Delantero",
    "position_raw": "Delantero",
    "position": "DEL",
    "age": "N/A",
    "number": "N/A",
    "market_value": "N/A",
    "source": "https://enelcamarin.cl/joomsport_team/a-oriente/?sid=166009"
  },
  {
    "name": "16. Paulo Villalón Delantero",
    "position_raw": "Delantero",
    "position": "DEL",
    "age": "N/A",
    "number": "N/A",
    "market_value": "N/A",
    "source": "https://enelcamarin.cl/joomsport_team/a-oriente/?sid=166009"
  },
  {
    "name": "Bastián Salazar Delantero",
    "position_raw": "Delantero",
    "position": "DEL",
    "age": "N/A",
    "number": "N/A",
    "market_value": "N/A",
    "source": "https://enelcamarin.cl/joomsport_team/a-oriente/?sid=166009"
  },
  {
    "name": "Matías Osorio Salazar Delantero",
    "position_raw": "Delantero",
    "position": "DEL",
    "age": "N/A",
    "number": "N/A",
    "market_value": "N/A",
    "source": "https://enelcamarin.cl/joomsport_team/a-oriente/?sid=166009"
  },
  {
    "name": "Pablo Pereira González Delantero",
    "position_raw": "Delantero",
    "position": "DEL",
    "age": "N/A",
    "number": "N/A",
    "market_value": "N/A",
    "source": "https://enelcamarin.cl/joomsport_team/a-oriente/?sid=166009"
  },
  {
    "name": "Emanuel Vargas Delantero",
    "position_raw": "Delantero",
    "position": "DEL",
    "age": "N/A",
    "number": "N/A",
    "market_value": "N/A",
    "source": "https://enelcamarin.cl/joomsport_team/a-oriente/?sid=166009"
  },
  {
    "name": "Vicente Caro Delantero",
    "position_raw": "Delantero",
    "position": "DEL",
    "age": "N/A",
    "number": "N/A",
    "market_value": "N/A",
    "source": "https://enelcamarin.cl/joomsport_team/a-oriente/?sid=166009"
  },
  {
    "name": "DT. Gonzalo Rojas Entrenador",
    "position_raw": "N/A",
    "position": "N/A",
    "age": "N/A",
    "number": "N/A",
    "market_value": "N/A",
    "source": "https://enelcamarin.cl/joomsport_team/a-oriente/?sid=166009"
  },
  {
    "name": "DT. Dennis Contreras Entrenador",
    "position_raw": "N/A",
    "position": "N/A",
    "age": "N/A",
    "number": "N/A",
    "market_value": "N/A",
    "source": "https://enelcamarin.cl/joomsport_team/a-oriente/?sid=166009"
  },
  {
    "name": "DT. Agustín Salvatierra Entrenador",
    "position_raw": "N/A",
    "position": "N/A",
    "age": "N/A",
    "number": "N/A",
    "market_value": "N/A",
    "source": "https://enelcamarin.cl/joomsport_team/a-oriente/?sid=166009"
  },
  {
    "name": "12. Nicolás Covarrubias",
    "position_raw": "N/A",
    "position": "N/A",
    "age": "N/A",
    "number": "N/A",
    "market_value": "N/A",
    "source": "https://enelcamarin.cl/joomsport_team/a-oriente/?sid=166009"
  },
  {
    "name": "Nicolás Guerra Villalobos",
    "position_raw": "N/A",
    "position": "N/A",
    "age": "N/A",
    "number": "N/A",
    "market_value": "N/A",
    "source": "https://enelcamarin.cl/joomsport_team/a-oriente/?sid=166009"
  },
  {
    "name": "Felipe Asenjo",
    "position_raw": "N/A",
    "position": "N/A",
    "age": "N/A",
    "number": "N/A",
    "market_value": "N/A",
    "source": "https://enelcamarin.cl/joomsport_team/a-oriente/?sid=166009"
  },
  {
    "name": "Gustavo Javier Gómez",
    "position_raw": "N/A",
    "position": "N/A",
    "age": "N/A",
    "number": "N/A",
    "market_value": "N/A",
    "source": "https://enelcamarin.cl/joomsport_team/a-oriente/?sid=166009"
  },
  {
    "name": "Víctor Bravo",
    "position_raw": "N/A",
    "position": "N/A",
    "age": "N/A",
    "number": "N/A",
    "market_value": "N/A",
    "source": "https://enelcamarin.cl/joomsport_team/a-oriente/?sid=166009"
  },
  {
    "name": "21. Gabriel Gómez",
    "position_raw": "N/A",
    "position": "N/A",
    "age": "N/A",
    "number": "N/A",
    "market_value": "N/A",
    "source": "https://enelcamarin.cl/joomsport_team/a-oriente/?sid=166009"
  },
  {
    "name": "Joshua Villarroel",
    "position_raw": "N/A",
    "position": "N/A",
    "age": "N/A",
    "number": "N/A",
    "market_value": "N/A",
    "source": "https://enelcamarin.cl/joomsport_team/a-oriente/?sid=166009"
  },
  {
    "name": "Ronald Melo",
    "position_raw": "N/A",
    "position": "N/A",
    "age": "N/A",
    "number": "N/A",
    "market_value": "N/A",
    "source": "https://enelcamarin.cl/joomsport_team/a-oriente/?sid=166009"
  },
  {
    "name": "Martín Pérez",
    "position_raw": "N/A",
    "position": "N/A",
    "age": "N/A",
    "number": "N/A",
    "market_value": "N/A",
    "source": "https://enelcamarin.cl/joomsport_team/a-oriente/?sid=166009"
  },
  {
    "name": "Abraham Lobos",
    "position_raw": "N/A",
    "position": "N/A",
    "age": "N/A",
    "number": "N/A",
    "market_value": "N/A",
    "source": "https://enelcamarin.cl/joomsport_team/a-oriente/?sid=166009"
  },
  {
    "name": "Marcelo Cubillos",
    "position_raw": "N/A",
    "position": "N/A",
    "age": "N/A",
    "number": "N/A",
    "market_value": "N/A",
    "source": "https://enelcamarin.cl/joomsport_team/a-oriente/?sid=166009"
  },
  {
    "name": "1. Lucas Guimpert",
    "position_raw": "N/A",
    "position": "N/A",
    "age": "N/A",
    "number": "N/A",
    "market_value": "N/A",
    "source": "https://enelcamarin.cl/joomsport_team/a-oriente/?sid=166009"
  },
  {
    "name": "Franco Polanco",
    "position_raw": "N/A",
    "position": "N/A",
    "age": "N/A",
    "number": "N/A",
    "market_value": "N/A",
    "source": "https://enelcamarin.cl/joomsport_team/a-oriente/?sid=166009"
  },
  {
    "name": "Carlos Garay",
    "position_raw": "N/A",
    "position": "N/A",
    "age": "N/A",
    "number": "N/A",
    "market_value": "N/A",
    "source": "https://enelcamarin.cl/joomsport_team/a-oriente/?sid=166009"
  },
  {
    "name": "Esteban Guzmán",
    "position_raw": "N/A",
    "position": "N/A",
    "age": "N/A",
    "number": "N/A",
    "market_value": "N/A",
    "source": "https://enelcamarin.cl/joomsport_team/a-oriente/?sid=166009"
  },
  {
    "name": "Christopher Delgado",
    "position_raw": "N/A",
    "position": "N/A",
    "age": "N/A",
    "number": "N/A",
    "market_value": "N/A",
    "source": "https://enelcamarin.cl/joomsport_team/a-oriente/?sid=166009"
  },
  {
    "name": "Sebastian Lara",
    "position_raw": "N/A",
    "position": "N/A",
    "age": "N/A",
    "number": "N/A",
    "market_value": "N/A",
    "source": "https://enelcamarin.cl/joomsport_team/a-oriente/?sid=166009"
  },
  {
    "name": "DT. Gonzalo Rojas",
    "position_raw": "N/A",
    "position": "N/A",
    "age": "N/A",
    "number": "N/A",
    "market_value": "N/A",
    "source": "https://enelcamarin.cl/joomsport_team/a-oriente/?sid=166009"
  },
  {
    "name": "Benjamín Maureira",
    "position_raw": "N/A",
    "position": "N/A",
    "age": "N/A",
    "number": "N/A",
    "market_value": "N/A",
    "source": "https://enelcamarin.cl/joomsport_team/a-oriente/?sid=166009"
  },
  {
    "name": "10. Jordan Moreno",
    "position_raw": "N/A",
    "position": "N/A",
    "age": "N/A",
    "number": "N/A",
    "market_value": "N/A",
    "source": "https://enelcamarin.cl/joomsport_team/a-oriente/?sid=166009"
  },
  {
    "name": "Vicente Barría",
    "position_raw": "N/A",
    "position": "N/A",
    "age": "N/A",
    "number": "N/A",
    "market_value": "N/A",
    "source": "https://enelcamarin.cl/joomsport_team/a-oriente/?sid=166009"
  },
  {
    "name": "Michael Ahumada",
    "position_raw": "N/A",
    "position": "N/A",
    "age": "N/A",
    "number": "N/A",
    "market_value": "N/A",
    "source": "https://enelcamarin.cl/joomsport_team/a-oriente/?sid=166009"
  },
  {
    "name": "Ignacio Muñoz Pérez",
    "position_raw": "N/A",
    "position": "N/A",
    "age": "N/A",
    "number": "N/A",
    "market_value": "N/A",
    "source": "https://enelcamarin.cl/joomsport_team/a-oriente/?sid=166009"
  },
  {
    "name": "Tomás Navarro",
    "position_raw": "N/A",
    "position": "N/A",
    "age": "N/A",
    "number": "N/A",
    "market_value": "N/A",
    "source": "https://enelcamarin.cl/joomsport_team/a-oriente/?sid=166009"
  },
  {
    "name": "Daglas Maldonado",
    "position_raw": "N/A",
    "position": "N/A",
    "age": "N/A",
    "number": "N/A",
    "market_value": "N/A",
    "source": "https://enelcamarin.cl/joomsport_team/a-oriente/?sid=166009"
  },
  {
    "name": "18. Antonio Bernedo",
    "position_raw": "N/A",
    "position": "N/A",
    "age": "N/A",
    "number": "N/A",
    "market_value": "N/A",
    "source": "https://enelcamarin.cl/joomsport_team/a-oriente/?sid=166009"
  },
  {
    "name": "Benjamín Troncoso",
    "position_raw": "N/A",
    "position": "N/A",
    "age": "N/A",
    "number": "N/A",
    "market_value": "N/A",
    "source": "https://enelcamarin.cl/joomsport_team/a-oriente/?sid=166009"
  },
  {
    "name": "Sebastián Muñoz Tejas",
    "position_raw": "N/A",
    "position": "N/A",
    "age": "N/A",
    "number": "N/A",
    "market_value": "N/A",
    "source": "https://enelcamarin.cl/joomsport_team/a-oriente/?sid=166009"
  },
  {
    "name": "9. Ricardo Guerrero Castillo",
    "position_raw": "N/A",
    "position": "N/A",
    "age": "N/A",
    "number": "N/A",
    "market_value": "N/A",
    "source": "https://enelcamarin.cl/joomsport_team/a-oriente/?sid=166009"
  },
  {
    "name": "1. Javier Cubillos",
    "position_raw": "N/A",
    "position": "N/A",
    "age": "N/A",
    "number": "N/A",
    "market_value": "N/A",
    "source": "https://enelcamarin.cl/joomsport_team/a-oriente/?sid=166009"
  },
  {
    "name": "7. Diego Araya",
    "position_raw": "N/A",
    "position": "N/A",
    "age": "N/A",
    "number": "N/A",
    "market_value": "N/A",
    "source": "https://enelcamarin.cl/joomsport_team/a-oriente/?sid=166009"
  },
  {
    "name": "Ignacio Saldías",
    "position_raw": "N/A",
    "position": "N/A",
    "age": "N/A",
    "number": "N/A",
    "market_value": "N/A",
    "source": "https://enelcamarin.cl/joomsport_team/a-oriente/?sid=166009"
  },
  {
    "name": "Francisco Villarroel",
    "position_raw": "N/A",
    "position": "N/A",
    "age": "N/A",
    "number": "N/A",
    "market_value": "N/A",
    "source": "https://enelcamarin.cl/joomsport_team/a-oriente/?sid=166009"
  },
  {
    "name": "Danilo Bustamante",
    "position_raw": "N/A",
    "position": "N/A",
    "age": "N/A",
    "number": "N/A",
    "market_value": "N/A",
    "source": "https://enelcamarin.cl/joomsport_team/a-oriente/?sid=166009"
  },
  {
    "name": "2. Julián Gálvez",
    "position_raw": "N/A",
    "position": "N/A",
    "age": "N/A",
    "number": "N/A",
    "market_value": "N/A",
    "source": "https://enelcamarin.cl/joomsport_team/a-oriente/?sid=166009"
  },
  {
    "name": "Esaú Burgos",
    "position_raw": "N/A",
    "position": "N/A",
    "age": "N/A",
    "number": "N/A",
    "market_value": "N/A",
    "source": "https://enelcamarin.cl/joomsport_team/a-oriente/?sid=166009"
  },
  {
    "name": "6. Martín Campos",
    "position_raw": "N/A",
    "position": "N/A",
    "age": "N/A",
    "number": "N/A",
    "market_value": "N/A",
    "source": "https://enelcamarin.cl/joomsport_team/a-oriente/?sid=166009"
  },
  {
    "name": "José Tomás Martínez",
    "position_raw": "N/A",
    "position": "N/A",
    "age": "N/A",
    "number": "N/A",
    "market_value": "N/A",
    "source": "https://enelcamarin.cl/joomsport_team/a-oriente/?sid=166009"
  },
  {
    "name": "8. Ignacio Guerrero",
    "position_raw": "N/A",
    "position": "N/A",
    "age": "N/A",
    "number": "N/A",
    "market_value": "N/A",
    "source": "https://enelcamarin.cl/joomsport_team/a-oriente/?sid=166009"
  },
  {
    "name": "José Recabal",
    "position_raw": "N/A",
    "position": "N/A",
    "age": "N/A",
    "number": "N/A",
    "market_value": "N/A",
    "source": "https://enelcamarin.cl/joomsport_team/a-oriente/?sid=166009"
  },
  {
    "name": "DT. Dennis Contreras",
    "position_raw": "N/A",
    "position": "N/A",
    "age": "N/A",
    "number": "N/A",
    "market_value": "N/A",
    "source": "https://enelcamarin.cl/joomsport_team/a-oriente/?sid=166009"
  },
  {
    "name": "18. John Araya",
    "position_raw": "N/A",
    "position": "N/A",
    "age": "N/A",
    "number": "N/A",
    "market_value": "N/A",
    "source": "https://enelcamarin.cl/joomsport_team/a-oriente/?sid=166009"
  },
  {
    "name": "11. Víctor Caroca",
    "position_raw": "N/A",
    "position": "N/A",
    "age": "N/A",
    "number": "N/A",
    "market_value": "N/A",
    "source": "https://enelcamarin.cl/joomsport_team/a-oriente/?sid=166009"
  },
  {
    "name": "Marcello Calderón",
    "position_raw": "N/A",
    "position": "N/A",
    "age": "N/A",
    "number": "N/A",
    "market_value": "N/A",
    "source": "https://enelcamarin.cl/joomsport_team/a-oriente/?sid=166009"
  },
  {
    "name": "Sebastián Leiva",
    "position_raw": "N/A",
    "position": "N/A",
    "age": "N/A",
    "number": "N/A",
    "market_value": "N/A",
    "source": "https://enelcamarin.cl/joomsport_team/a-oriente/?sid=166009"
  },
  {
    "name": "Brayan Quezada",
    "position_raw": "N/A",
    "position": "N/A",
    "age": "N/A",
    "number": "N/A",
    "market_value": "N/A",
    "source": "https://enelcamarin.cl/joomsport_team/a-oriente/?sid=166009"
  },
  {
    "name": "John Gómez Ruiz",
    "position_raw": "N/A",
    "position": "N/A",
    "age": "N/A",
    "number": "N/A",
    "market_value": "N/A",
    "source": "https://enelcamarin.cl/joomsport_team/a-oriente/?sid=166009"
  },
  {
    "name": "Kevin Aranda",
    "position_raw": "N/A",
    "position": "N/A",
    "age": "N/A",
    "number": "N/A",
    "market_value": "N/A",
    "source": "https://enelcamarin.cl/joomsport_team/a-oriente/?sid=166009"
  },
  {
    "name": "Diego Araya",
    "position_raw": "N/A",
    "position": "N/A",
    "age": "N/A",
    "number": "N/A",
    "market_value": "N/A",
    "source": "https://enelcamarin.cl/joomsport_team/a-oriente/?sid=166009"
  },
  {
    "name": "17. Sebastián Sasso",
    "position_raw": "N/A",
    "position": "N/A",
    "age": "N/A",
    "number": "N/A",
    "market_value": "N/A",
    "source": "https://enelcamarin.cl/joomsport_team/a-oriente/?sid=166009"
  },
  {
    "name": "Luciano Anzalone",
    "position_raw": "N/A",
    "position": "N/A",
    "age": "N/A",
    "number": "N/A",
    "market_value": "N/A",
    "source": "https://enelcamarin.cl/joomsport_team/a-oriente/?sid=166009"
  },
  {
    "name": "Rodrigo Vidal",
    "position_raw": "N/A",
    "position": "N/A",
    "age": "N/A",
    "number": "N/A",
    "market_value": "N/A",
    "source": "https://enelcamarin.cl/joomsport_team/a-oriente/?sid=166009"
  },
  {
    "name": "Jesrrel Gálvez",
    "position_raw": "N/A",
    "position": "N/A",
    "age": "N/A",
    "number": "N/A",
    "market_value": "N/A",
    "source": "https://enelcamarin.cl/joomsport_team/a-oriente/?sid=166009"
  },
  {
    "name": "16. Paulo Villalón",
    "position_raw": "N/A",
    "position": "N/A",
    "age": "N/A",
    "number": "N/A",
    "market_value": "N/A",
    "source": "https://enelcamarin.cl/joomsport_team/a-oriente/?sid=166009"
  },
  {
    "name": "José Luis Aedo",
    "position_raw": "N/A",
    "position": "N/A",
    "age": "N/A",
    "number": "N/A",
    "market_value": "N/A",
    "source": "https://enelcamarin.cl/joomsport_team/a-oriente/?sid=166009"
  },
  {
    "name": "Ariel Pizarro",
    "position_raw": "N/A",
    "position": "N/A",
    "age": "N/A",
    "number": "N/A",
    "market_value": "N/A",
    "source": "https://enelcamarin.cl/joomsport_team/a-oriente/?sid=166009"
  },
  {
    "name": "10. Alans Yañez",
    "position_raw": "N/A",
    "position": "N/A",
    "age": "N/A",
    "number": "N/A",
    "market_value": "N/A",
    "source": "https://enelcamarin.cl/joomsport_team/a-oriente/?sid=166009"
  },
  {
    "name": "Rodrigo Cancino",
    "position_raw": "N/A",
    "position": "N/A",
    "age": "N/A",
    "number": "N/A",
    "market_value": "N/A",
    "source": "https://enelcamarin.cl/joomsport_team/a-oriente/?sid=166009"
  },
  {
    "name": "Lucas Rojas",
    "position_raw": "N/A",
    "position": "N/A",
    "age": "N/A",
    "number": "N/A",
    "market_value": "N/A",
    "source": "https://enelcamarin.cl/joomsport_team/a-oriente/?sid=166009"
  },
  {
    "name": "DT. Agustín Salvatierra",
    "position_raw": "N/A",
    "position": "N/A",
    "age": "N/A",
    "number": "N/A",
    "market_value": "N/A",
    "source": "https://enelcamarin.cl/joomsport_team/a-oriente/?sid=166009"
  },
  {
    "name": "Bryan Escobar (2002)",
    "position_raw": "N/A",
    "position": "N/A",
    "age": "N/A",
    "number": "N/A",
    "market_value": "N/A",
    "source": "https://enelcamarin.cl/joomsport_team/a-oriente/?sid=166009"
  },
  {
    "name": "Luis Guzmán Morales",
    "position_raw": "N/A",
    "position": "N/A",
    "age": "N/A",
    "number": "N/A",
    "market_value": "N/A",
    "source": "https://enelcamarin.cl/joomsport_team/a-oriente/?sid=166009"
  },
  {
    "name": "Mauricio Aravena",
    "position_raw": "N/A",
    "position": "N/A",
    "age": "N/A",
    "number": "N/A",
    "market_value": "N/A",
    "source": "https://enelcamarin.cl/joomsport_team/a-oriente/?sid=166009"
  },
  {
    "name": "Bastián Salazar",
    "position_raw": "N/A",
    "position": "N/A",
    "age": "N/A",
    "number": "N/A",
    "market_value": "N/A",
    "source": "https://enelcamarin.cl/joomsport_team/a-oriente/?sid=166009"
  },
  {
    "name": "Matías Osorio Salazar",
    "position_raw": "N/A",
    "position": "N/A",
    "age": "N/A",
    "number": "N/A",
    "market_value": "N/A",
    "source": "https://enelcamarin.cl/joomsport_team/a-oriente/?sid=166009"
  },
  {
    "name": "Pablo Pereira González",
    "position_raw": "N/A",
    "position": "N/A",
    "age": "N/A",
    "number": "N/A",
    "market_value": "N/A",
    "source": "https://enelcamarin.cl/joomsport_team/a-oriente/?sid=166009"
  },
  {
    "name": "Emanuel Vargas",
    "position_raw": "N/A",
    "position": "N/A",
    "age": "N/A",
    "number": "N/A",
    "market_value": "N/A",
    "source": "https://enelcamarin.cl/joomsport_team/a-oriente/?sid=166009"
  },
  {
    "name": "Benjamín Guerrero",
    "position_raw": "N/A",
    "position": "N/A",
    "age": "N/A",
    "number": "N/A",
    "market_value": "N/A",
    "source": "https://enelcamarin.cl/joomsport_team/a-oriente/?sid=166009"
  },
  {
    "name": "Agustín Flores",
    "position_raw": "N/A",
    "position": "N/A",
    "age": "N/A",
    "number": "N/A",
    "market_value": "N/A",
    "source": "https://enelcamarin.cl/joomsport_team/a-oriente/?sid=166009"
  },
  {
    "name": "Brian Sevich",
    "position_raw": "N/A",
    "position": "N/A",
    "age": "N/A",
    "number": "N/A",
    "market_value": "N/A",
    "source": "https://enelcamarin.cl/joomsport_team/a-oriente/?sid=166009"
  },
  {
    "name": "Emir González",
    "position_raw": "N/A",
    "position": "N/A",
    "age": "N/A",
    "number": "N/A",
    "market_value": "N/A",
    "source": "https://enelcamarin.cl/joomsport_team/a-oriente/?sid=166009"
  },
  {
    "name": "Darío Aravena",
    "position_raw": "N/A",
    "position": "N/A",
    "age": "N/A",
    "number": "N/A",
    "market_value": "N/A",
    "source": "https://enelcamarin.cl/joomsport_team/a-oriente/?sid=166009"
  },
  {
    "name": "Dery Varela",
    "position_raw": "N/A",
    "position": "N/A",
    "age": "N/A",
    "number": "N/A",
    "market_value": "N/A",
    "source": "https://enelcamarin.cl/joomsport_team/a-oriente/?sid=166009"
  },
  {
    "name": "Víctor Cisterna",
    "position_raw": "N/A",
    "position": "N/A",
    "age": "N/A",
    "number": "N/A",
    "market_value": "N/A",
    "source": "https://enelcamarin.cl/joomsport_team/a-oriente/?sid=166009"
  },
  {
    "name": "Jorge Cid",
    "position_raw": "N/A",
    "position": "N/A",
    "age": "N/A",
    "number": "N/A",
    "market_value": "N/A",
    "source": "https://enelcamarin.cl/joomsport_team/a-oriente/?sid=166009"
  },
  {
    "name": "Alonso Montecinos",
    "position_raw": "N/A",
    "position": "N/A",
    "age": "N/A",
    "number": "N/A",
    "market_value": "N/A",
    "source": "https://enelcamarin.cl/joomsport_team/a-oriente/?sid=166009"
  },
  {
    "name": "Dhariel Núñez",
    "position_raw": "N/A",
    "position": "N/A",
    "age": "N/A",
    "number": "N/A",
    "market_value": "N/A",
    "source": "https://enelcamarin.cl/joomsport_team/a-oriente/?sid=166009"
  },
  {
    "name": "Maximiliano Godoy Forne",
    "position_raw": "N/A",
    "position": "N/A",
    "age": "N/A",
    "number": "N/A",
    "market_value": "N/A",
    "source": "https://enelcamarin.cl/joomsport_team/a-oriente/?sid=166009"
  },
  {
    "name": "Jordan Olea",
    "position_raw": "N/A",
    "position": "N/A",
    "age": "N/A",
    "number": "N/A",
    "market_value": "N/A",
    "source": "https://enelcamarin.cl/joomsport_team/a-oriente/?sid=166009"
  },
  {
    "name": "Francisco Valenzuela",
    "position_raw": "N/A",
    "position": "N/A",
    "age": "N/A",
    "number": "N/A",
    "market_value": "N/A",
    "source": "https://enelcamarin.cl/joomsport_team/a-oriente/?sid=166009"
  },
  {
    "name": "Vicente Caro",
    "position_raw": "N/A",
    "position": "N/A",
    "age": "N/A",
    "number": "N/A",
    "market_value": "N/A",
    "source": "https://enelcamarin.cl/joomsport_team/a-oriente/?sid=166009"
  }
]